{"cameraMode":{"drawMode":0,"name":"Shaded","section":"Shading Mode"},"sceneLighting":true,"audioPlay":false,"sceneViewState":{"showFog":true,"showMaterialUpdate":false,"showSkybox":true,"showFlares":true,"showImageEffects":true,"showParticleSystems":true},"in2DMode":false,"pivot":{"x":-1.9503023624420167,"y":0.6286935806274414,"z":-0.6955547332763672},"rotation":{"x":-0.3935757577419281,"y":0.1213410422205925,"z":-0.05249789357185364,"w":-0.9097442626953125},"size":7.102365970611572,"orthographic":false}