{"cameraMode":{"drawMode":0,"name":"Shaded","section":"Shading Mode"},"sceneLighting":true,"audioPlay":false,"sceneViewState":{"showFog":true,"showMaterialUpdate":false,"showSkybox":true,"showFlares":true,"showImageEffects":true,"showParticleSystems":true},"in2DMode":false,"pivot":{"x":-3.6785449981689455,"y":-6.622645854949951,"z":-11.775461196899414},"rotation":{"x":0.06190197542309761,"y":-0.9373025894165039,"z":0.26274409890174868,"w":0.22073256969451905},"size":11.828885078430176,"orthographic":false}